{
  "AC71302241": {
    "contest_id": "abc434",
    "language": "C++23 (GCC 15.2.0)",
    "path": "atcoder\\abc434\\abc434A Balloon_Trip.cpp",
    "platform": "AtCoder",
    "problem_index": "A",
    "problem_name": "Balloon Trip",
    "problem_url": "https://atcoder.jp/contests/abc434/tasks/abc434_a",
    "submission_id": "AC71302241",
    "submission_url": "https://atcoder.jp/contests/abc434/submissions/71302241",
    "tags": [
      "AtCoder",
      "*100"
    ],
    "timestamp": "Nov/29/2025 18:05"
  },
  "AC71306451": {
    "contest_id": "abc434",
    "language": "C++23 (GCC 15.2.0)",
    "path": "atcoder\\abc434\\abc434B Bird_Watching.cpp",
    "platform": "AtCoder",
    "problem_index": "B",
    "problem_name": "Bird Watching",
    "problem_url": "https://atcoder.jp/contests/abc434/tasks/abc434_b",
    "submission_id": "AC71306451",
    "submission_url": "https://atcoder.jp/contests/abc434/submissions/71306451",
    "tags": [
      "AtCoder",
      "*200"
    ],
    "timestamp": "Nov/29/2025 18:10"
  },
  "AC71315182": {
    "contest_id": "abc434",
    "language": "C++23 (GCC 15.2.0)",
    "path": "atcoder\\abc434\\abc434C Flapping_Takahashi.cpp",
    "platform": "AtCoder",
    "problem_index": "C",
    "problem_name": "Flapping Takahashi",
    "problem_url": "https://atcoder.jp/contests/abc434/tasks/abc434_c",
    "submission_id": "AC71315182",
    "submission_url": "https://atcoder.jp/contests/abc434/submissions/71315182",
    "tags": [
      "AtCoder",
      "*300"
    ],
    "timestamp": "Nov/29/2025 18:26"
  }
}